{
  "schemaVersion": 1,
  "taskId": "T02",
  "unitId": "M003/S02/T02",
  "timestamp": 1776765850563,
  "passed": false,
  "discoverySource": "task-plan",
  "checks": [
    {
      "command": "pnpm --dir apps/mobile exec vitest run tests/mobile-continuity.unit.test.ts tests/continuity-contract.unit.test.ts",
      "exitCode": 0,
      "durationMs": 1250,
      "verdict": "pass"
    },
    {
      "command": "pnpm --dir apps/mobile check",
      "exitCode": 0,
      "durationMs": 2342,
      "verdict": "pass"
    }
  ],
  "retryAttempt": 1,
  "maxRetries": 2,
  "postExecutionChecks": [
    {
      "category": "import",
      "target": "apps/mobile/src/routes/+layout.ts:8",
      "passed": false,
      "message": "Import './$types' in apps/mobile/src/routes/+layout.ts:8 does not resolve to an existing file",
      "blocking": true
    }
  ]
}
